MODE/__init__.py
MODE/deconvolution.py
MODE/jnmf.py
MODE/model.py
MODE/simulation.py
MODE/train.py
MODE/utils.py
MODE_omics-0.1.1.dist-info/LICENSE
MODE_omics-0.1.1.dist-info/METADATA
MODE_omics-0.1.1.dist-info/WHEEL
MODE_omics-0.1.1.dist-info/top_level.txt
MODE_omics-0.1.1.dist-info/RECORD
